{"cameraMode":{"drawMode":0,"name":"Shaded","section":"Shading Mode"},"sceneLighting":true,"audioPlay":false,"sceneViewState":{"showFog":true,"showMaterialUpdate":false,"showSkybox":true,"showFlares":true,"showImageEffects":true,"showParticleSystems":true},"in2DMode":false,"pivot":{"x":-0.546032190322876,"y":-3.6039419174194338,"z":-2.8173277378082277},"rotation":{"x":-0.25544309616088869,"y":-0.0052237738855183128,"z":0.0013801574241369963,"w":-0.9668093323707581},"size":7.160407066345215,"orthographic":false}